Workbook

Sheet Instructions
A1: 1. If you would like to calculate your expenses in a currency other than USD, you can fill in cell B1 with the conversion between your currency and USD (using Google's currency converter). Then, enter amounts in column D using your own currency, and they will automatically convert to USD in column F.
A2: 2. We suggest a contingency buffer of 5% of your grant. Cell F2 will automatically calculate this as you add line items below (don't add anything above it).
A3: 3. You don't have to use this template for your grant budget, but we ask that you submit your application budget in a spreadsheet format.
A4: 4. If you are applying for a range of funding scenarios (e.g., minimum, mainline, and maximum), please use a new tab for each scenario. To duplicate the budget template, right click the name of the tab, then select 'Duplicate'. Please name the tab with the funding scenario (e.g. "Mainline").
A5: 5. Please email grants@centreforeffectivealtruism.org if you have any problems or suggestions for this template.
A7: AcquaHT notes: This file has one scenario (Mainline, $75,000). B1 = 1 because all amounts are entered in USD. Yellow cells are inputs; all other numbers are formulas. The 'Detail' tab shows how each category adds up, and 'Assumptions' lists the reasoning.

Sheet Mainline
A1: Currency conversion (1 unit of your currency = ? USD) | B1: 1 | C1: 1 = amounts already in USD
A2: Contingency buffer | B2: Contingency (% of line items) | C2: 0.071428571 | E2: USD | F2: =ROUND(F11*C2,0)
A4: Category | B4: What it covers | C4: Timeline | D4: Amount (your currency) | E4: % of total | F4: Amount (USD)
A5: Prototype build (1,000 L/day module) | B5: Materials and assembly for one full-size module | C5: Months 1–6 | D5: =Detail!E11 | E5: =F5/$F$13 | F5: =D5*$B$1
A6: Lab testing | B6: Equipment, instrumentation, third-party WHO/BIS water tests, environmental compliance | C6: Months 5–9 | D6: =Detail!E17 | E6: =F6/$F$13 | F6: =D6*$B$1
A7: Field validation | B7: Deployment, 6 months of monitoring, travel | C7: Months 9–15 | D7: =Detail!E27 | E7: =F7/$F$13 | F7: =D7*$B$1
A8: Stipend for 1 FTE | B8: One full-time engineer for 18 months | C8: Months 1–18 | D8: =Detail!E30 | E8: =F8/$F$13 | F8: =D8*$B$1
A9: Open-source package | B9: Documentation, video, translation into Hindi, French, Spanish | C9: Months 15–18 | D9: =Detail!E35 | E9: =F9/$F$13 | F9: =D9*$B$1
A11: Subtotal (line items) | D11: =SUM(D5:D9) | E11: =F11/$F$13 | F11: =SUM(F5:F9)
A12: Contingency buffer (from F2) | D12: =F2/$B$1 | E12: =F12/$F$13 | F12: =F2
A13: TOTAL REQUESTED | D13: =D11+D12 | E13: =F13/$F$13 | F13: =F11+F12
A15: Requested amount (USD) | F15: 75000
A16: Check: total matches request | F16: =IF(F13=F15,"OK","MISMATCH")
A17: Total project budget size (USD) | F17: =F13

Sheet Detail
A1: AcquaHT – Detailed budget breakdown (USD)
A3: Category | B3: Line item | C3: Qty | D3: Unit cost | E3: Total (USD)
A4: Prototype build (1,000 L/day module) | B4: Refrigeration system (compressor, evaporator, condenser coils) | C4: 1 | D4: 6500 | E4: =C4*D4
A5: Prototype build (1,000 L/day module) | B5: Air handling (fans, ducting, air filters) | C5: 1 | D5: 2500 | E5: =C5*D5
A6: Prototype build (1,000 L/day module) | B6: Water treatment (sediment + carbon filters, UV, mineralisation) | C6: 1 | D6: 2500 | E6: =C6*D6
A7: Prototype build (1,000 L/day module) | B7: Storage tank, pumps, food-grade plumbing | C7: 1 | D7: 1500 | E7: =C7*D7
A8: Prototype build (1,000 L/day module) | B8: Controller, sensors (humidity, temp, flow, TDS), power electronics | C8: 1 | D8: 2500 | E8: =C8*D8
A9: Prototype build (1,000 L/day module) | B9: Frame, enclosure, insulation | C9: 1 | D9: 2000 | E9: =C9*D9
A10: Prototype build (1,000 L/day module) | B10: Assembly labour, fabrication, tools, consumables | C10: 1 | D10: 2500 | E10: =C10*D10
B11: Subtotal – Prototype build (1,000 L/day module) | E11: =SUM(E4:E10)
A13: Lab testing | B13: Instrumentation (power meter, data logger, psychrometer, flow meters) | C13: 1 | D13: 3500 | E13: =C13*D13
A14: Lab testing | B14: Water quality tests to BIS IS 10500 / WHO guidelines (accredited lab) | C14: 4 | D14: 1000 | E14: =C14*D14
A15: Lab testing | B15: Environmental chamber time (output vs humidity/temp curve) | C15: 1 | D15: 1500 | E15: =C15*D15
A16: Lab testing | B16: Environmental compliance (refrigerant handling, electrical safety) | C16: 1 | D16: 1000 | E16: =C16*D16
B17: Subtotal – Lab testing | E17: =SUM(E13:E16)
A19: Field validation (6 months) | B19: Transport and installation at field site | C19: 1 | D19: 3000 | E19: =C19*D19
A20: Field validation (6 months) | B20: Site preparation (base, shelter, electrical connection) | C20: 1 | D20: 2500 | E20: =C20*D20
A21: Field validation (6 months) | B21: Electricity for 6 months of operation | C21: 6 | D21: 500 | E21: =C21*D21
A22: Field validation (6 months) | B22: Remote monitoring (IoT logger, SIM data, dashboard) | C22: 1 | D22: 1500 | E22: =C22*D22
A23: Field validation (6 months) | B23: Monthly water quality tests during field trial | C23: 6 | D23: 500 | E23: =C23*D23
A24: Field validation (6 months) | B24: Local operator / caretaker | C24: 6 | D24: 250 | E24: =C24*D24
A25: Field validation (6 months) | B25: Travel for site visits (team) | C25: 6 | D25: 750 | E25: =C25*D25
A26: Field validation (6 months) | B26: Maintenance and spare parts | C26: 1 | D26: 1000 | E26: =C26*D26
B27: Subtotal – Field validation (6 months) | E27: =SUM(E19:E26)
A29: Stipend (1 FTE, 18 months) | B29: Engineer / project lead stipend (months) | C29: 18 | D29: 833.33333 | E29: =C29*D29
B30: Subtotal – Stipend (1 FTE, 18 months) | E30: =SUM(E29:E29)
A32: Open-source package | B32: Technical documentation, drawings, bill of materials | C32: 1 | D32: 2000 | E32: =C32*D32
A33: Open-source package | B33: Build and operation video | C33: 1 | D33: 1500 | E33: =C33*D33
A34: Open-source package | B34: Translation into Hindi, French, Spanish | C34: 3 | D34: 500 | E34: =C34*D34
B35: Subtotal – Open-source package | E35: =SUM(E32:E34)
B37: Total of line items (before contingency) | E37: =E11+E17+E27+E30+E35

Sheet Assumptions
A1: Assumptions
A3: Currency | B3: All amounts are in USD, so B1 on the Mainline tab is 1. To work in INR, set B1 to the USD value of ₹1 and enter INR in column D.
A4: Scenario | B4: One funding scenario: Mainline, $75,000. This is also the full project budget.
A5: Contingency | B5: $5,000, which is 7.1% of the $70,000 line items (6.7% of the $75,000 total). This is above the template's suggested 5% because the prototype is a first full-size build and hardware prices can move.
A6: Prototype | B6: One 1,000 L/day module. Prices are estimates from Indian suppliers and include fabrication and assembly labour.
A7: Lab testing | B7: Water tested against BIS IS 10500 and WHO drinking-water guidelines at an accredited lab, 4 rounds. Includes instruments to log energy use (kWh per litre) and output across humidity and temperature.
A8: Field validation | B8: One field site in India, 6 months of running with remote data logging, monthly water tests, and regular site visits.
A9: Stipend | B9: One full-time engineer for 18 months at about $833 per month.
A10: Open-source package | B10: Drawings, bill of materials, build guide, and a video, released under an open licence. Translated into Hindi, French and Spanish.
A11: Timeline | B11: 18 months in total. Build (months 1–6), lab testing (5–9), field trial (9–15), open-source release (15–18).
A12: Detail tab | B12: The line-item split inside each category is our best current estimate. Category totals are fixed; we may move money between line items inside a category.
